Compare_SQL_RedShift.py
DaskUtil.py
MasterClass.py
Compare_SQL_Redshift_Framework-0.0.2.dist-info/LICENSE.txt
Compare_SQL_Redshift_Framework-0.0.2.dist-info/METADATA
Compare_SQL_Redshift_Framework-0.0.2.dist-info/WHEEL
Compare_SQL_Redshift_Framework-0.0.2.dist-info/top_level.txt
Compare_SQL_Redshift_Framework-0.0.2.dist-info/RECORD
