Metadata-Version: 2.1
Name: Compare-SQL-Redshift-Framework
Version: 0.0.2
Summary: Compare_SQL_Redshift_Framework Test Upload
Home-page: https://acapgit.acacceptance.com/projects/AWA/repos/libraries/browse
Author: Rajnish
Author-email: rajnish.kumar@acacceptance.com
License: UNKNOWN
Platform: UNKNOWN
Classifier: Programming Language :: Python :: 3
Classifier: Programming Language :: Python :: 3.6
Classifier: Programming Language :: Python :: 3.7
Classifier: License :: OSI Approved :: GNU General Public License v2 or later (GPLv2+)
Classifier: Operating System :: OS Independent
Provides-Extra: dev
Requires-Dist: pytest (>=3.7) ; extra == 'dev'
